Verilog/main.v
module dff(
    input wire clk,
    input wire rst,
    input wire d,
    output reg q
);
always @(posedge clk) begin
    if (rst)
        q <= 0;
    else
        q <= d;
end
endmodule

module pg_logic (
    input wire [4:0] a,
    input wire [4:0] b,
    output wire [4:0] p,    
    output wire [4:0] g        
);
    assign p   = a ^ b;   
    assign g   = a & b; 
endmodule


module cla_carry (
    input wire [4:0] p,
    input wire [4:0] g,
    output wire [5:0] c
);
    wire [4:0] g_bar;
    wire t2_1, t3_1, t3_2, t4_1, t4_2, t4_3, t5_1, t5_2, t5_3, t5_4;
    
    assign c[0] = 1'b0;
    assign c[1] = g[0];
    
    // Invert g signals
    not(g_bar[1], g[1]);
    not(g_bar[2], g[2]);
    not(g_bar[3], g[3]);
    not(g_bar[4], g[4]);
    
    // c[2] = g[1] | (p[1] & g[0])
    nand(t2_1, p[1], g[0]);
    nand(c[2], g_bar[1], t2_1);

    // c[3] = g[2] | (p[2] & g[1]) | (p[2] & p[1] & g[0])
    nand(t3_1, p[2], g[1]);
    nand(t3_2, p[2], p[1], g[0]);
    nand(c[3], g_bar[2], t3_1, t3_2);

    // c[4] = g[3] | (p[3] & g[2]) | (p[3] & p[2] & g[1]) | (p[3] & p[2] & p[1] & g[0])
    nand(t4_1, p[3], g[2]);
    nand(t4_2, p[3], p[2], g[1]);
    nand(t4_3, p[3], p[2], p[1], g[0]);
    nand(c[4], g_bar[3], t4_1, t4_2, t4_3);
    
    // c[5] = g[4] | (p[4] & g[3]) | (p[4] & p[3] & g[2]) | (p[4] & p[3] & p[2] & g[1]) | (p[4] & p[3] & p[2] & p[1] & g[0])
    nand(t5_1, p[4], g[3]);
    nand(t5_2, p[4], p[3], g[2]);
    nand(t5_3, p[4], p[3], p[2], g[1]);
    nand(t5_4, p[4], p[3], p[2], p[1], g[0]);
    nand(c[5], g_bar[4], t5_1, t5_2, t5_3, t5_4);
endmodule


module cla_adder_5bit (
    input wire clk,
    input wire rst,
    input wire [4:0] a,
    input wire [4:0] b,
    output wire [4:0] sum,
    output wire cout
);

    wire [4:0] a_reg, b_reg;
    wire [4:0] p, g;
    wire [5:0] c;
    wire [4:0] sum_int;
    wire cout_int;
    
    dff dff_a0 (.clk(clk), .rst(rst), .d(a[0]), .q(a_reg[0]));
    dff dff_a1 (.clk(clk), .rst(rst), .d(a[1]), .q(a_reg[1]));
    dff dff_a2 (.clk(clk), .rst(rst), .d(a[2]), .q(a_reg[2]));
    dff dff_a3 (.clk(clk), .rst(rst), .d(a[3]), .q(a_reg[3]));
    dff dff_a4 (.clk(clk), .rst(rst), .d(a[4]), .q(a_reg[4]));
    
    dff dff_b0 (.clk(clk), .rst(rst), .d(b[0]), .q(b_reg[0]));
    dff dff_b1 (.clk(clk), .rst(rst), .d(b[1]), .q(b_reg[1]));
    dff dff_b2 (.clk(clk), .rst(rst), .d(b[2]), .q(b_reg[2]));
    dff dff_b3 (.clk(clk), .rst(rst), .d(b[3]), .q(b_reg[3]));
    dff dff_b4 (.clk(clk), .rst(rst), .d(b[4]), .q(b_reg[4]));
    
    pg_logic pg (
        .a(a_reg),
        .b(b_reg),
        .p(p),
        .g(g)
    );
    
    cla_carry cla (
        .p(p),
        .g(g),
        .c(c)
    );
    assign sum_int = p ^ c[4:0];
    assign cout_int = c[5];
    
    dff dff_sum0 (.clk(clk), .rst(rst), .d(sum_int[0]), .q(sum[0]));
    dff dff_sum1 (.clk(clk), .rst(rst), .d(sum_int[1]), .q(sum[1]));
    dff dff_sum2 (.clk(clk), .rst(rst), .d(sum_int[2]), .q(sum[2]));
    dff dff_sum3 (.clk(clk), .rst(rst), .d(sum_int[3]), .q(sum[3]));
    dff dff_sum4 (.clk(clk), .rst(rst), .d(sum_int[4]), .q(sum[4]));
    dff dff_cout (.clk(clk), .rst(rst), .d(cout_int), .q(cout));
    
endmodule

Verilog/tb_all.v
`timescale 1ns/1ps

module tb_cla_adder_5bit_exhaustive;

    // DUT inputs
    reg clk;
    reg rst;
    reg [4:0] a;
    reg [4:0] b;

    // DUT outputs
    wire [4:0] sum;
    wire cout;

    // Reference model outputs
    reg [5:0] expected;

    // Instantiate the DUT
    cla_adder_5bit uut (
        .clk(clk),
        .rst(rst),
        .a(a),
        .b(b),
        .sum(sum),
        .cout(cout)
    );

    // Clock generation (period = 10 ns)
    always #5 clk = ~clk;

    integer i, j, k;
    integer error_count = 0;

    // Dump waveforms for GTKWave
    initial begin
        $dumpfile("cla_adder_5bit_exhaustive.vcd");
        $dumpvars(0, tb_cla_adder_5bit_exhaustive);
    end

    initial begin
        // Initialize
        clk = 0;
        rst = 1;
        a = 0;
        b = 0;

        // Apply reset
        #20;
        rst = 0;

        $display("Starting exhaustive 5-bit CLA verification...");
        $display("Note: c0 is always 0 as per project specification");
        $display("-----------------------------------------------------------");
        $display("   Time |   a   |   b   | sum | cout | expected_sum | PASS?");
        $display("-----------------------------------------------------------");

        // Run all 1024 input combinations (cin always 0)
        for (i = 0; i < 32; i = i + 1) begin
            for (j = 0; j < 32; j = j + 1) begin
                a = i[4:0];
                b = j[4:0];

                // Apply input
                #10;

                // Wait for registered output (one extra clock cycle delay)
                #10;

                // Compute expected result (cin = 0)
                expected = a + b;


                // Display result
                $display("%6t | %05b | %05b | %05b |  %b  |    %06b    | %s",
                         $time, a, b, sum, cout, expected,
                         (({cout, sum} == expected) ? "PASS" : "FAIL"));

                // Check correctness
                if ({cout, sum} !== expected) begin
                    error_count = error_count + 1;
                end
            end
        end

        // Final summary
        $display("-----------------------------------------------------------");
        if (error_count == 0)
            $display("✅ All 1024 test cases PASSED successfully!");
        else
            $display("❌ %0d test cases FAILED!", error_count);

        $display("-----------------------------------------------------------");
        $finish;
    end

endmodule

Verilog/cla_adder_5bit_exhaustive.vcd
$date
	Wed Dec 03 20:28:42 2025
$end
$version
	Icarus Verilog
$end
$timescale
	1ps
$end
$scope module tb_cla_adder_5bit_exhaustive $end
$var wire 5 ! sum [4:0] $end
$var wire 1 " cout $end
$var reg 5 # a [4:0] $end
$var reg 5 $ b [4:0] $end
$var reg 1 % clk $end
$var reg 6 & expected [5:0] $end
$var reg 1 ' rst $end
$var integer 32 ( error_count [31:0] $end
$var integer 32 ) i [31:0] $end
$var integer 32 * j [31:0] $end
$scope module uut $end
$var wire 5 + a [4:0] $end
$var wire 5 , b [4:0] $end
$var wire 1 % clk $end
$var wire 1 ' rst $end
$var wire 5 - sum_int [4:0] $end
$var wire 5 . sum [4:0] $end
$var wire 5 / p [4:0] $end
$var wire 5 0 g [4:0] $end
$var wire 1 1 cout_int $end
$var wire 1 " cout $end
$var wire 6 2 c [5:0] $end
$var wire 5 3 b_reg [4:0] $end
$var wire 5 4 a_reg [4:0] $end
$scope module cla $end
$var wire 1 5 t2_1 $end
$var wire 1 6 t3_1 $end
$var wire 1 7 t3_2 $end
$var wire 1 8 t4_1 $end
$var wire 1 9 t4_2 $end
$var wire 1 : t4_3 $end
$var wire 1 ; t5_1 $end
$var wire 1 < t5_2 $end
$var wire 1 = t5_3 $end
$var wire 1 > t5_4 $end
$var wire 5 ? p [4:0] $end
$var wire 5 @ g_bar [4:0] $end
$var wire 5 A g [4:0] $end
$var wire 6 B c [5:0] $end
$upscope $end
$scope module dff_a0 $end
$var wire 1 % clk $end
$var wire 1 C d $end
$var wire 1 ' rst $end
$var reg 1 D q $end
$upscope $end
$scope module dff_a1 $end
$var wire 1 % clk $end
$var wire 1 E d $end
$var wire 1 ' rst $end
$var reg 1 F q $end
$upscope $end
$scope module dff_a2 $end
$var wire 1 % clk $end
$var wire 1 G d $end
$var wire 1 ' rst $end
$var reg 1 H q $end
$upscope $end
$scope module dff_a3 $end
$var wire 1 % clk $end
$var wire 1 I d $end
$var wire 1 ' rst $end
$var reg 1 J q $end
$upscope $end
$scope module dff_a4 $end
$var wire 1 % clk $end
$var wire 1 K d $end
$var wire 1 ' rst $end
$var reg 1 L q $end
$upscope $end
$scope module dff_b0 $end
$var wire 1 % clk $end
$var wire 1 M d $end
$var wire 1 ' rst $end
$var reg 1 N q $end
$upscope $end
$scope module dff_b1 $end
$var wire 1 % clk $end
$var wire 1 O d $end
$var wire 1 ' rst $end
$var reg 1 P q $end
$upscope $end
$scope module dff_b2 $end
$var wire 1 % clk $end
$var wire 1 Q d $end
$var wire 1 ' rst $end
$var reg 1 R q $end
$upscope $end
$scope module dff_b3 $end
$var wire 1 % clk $end
$var wire 1 S d $end
$var wire 1 ' rst $end
$var reg 1 T q $end
$upscope $end
$scope module dff_b4 $end
$var wire 1 % clk $end
$var wire 1 U d $end
$var wire 1 ' rst $end
$var reg 1 V q $end
$upscope $end
$scope module dff_cout $end
$var wire 1 % clk $end
$var wire 1 1 d $end
$var wire 1 ' rst $end
$var reg 1 " q $end
$upscope $end
$scope module dff_sum0 $end
$var wire 1 % clk $end
$var wire 1 W d $end
$var wire 1 ' rst $end
$var reg 1 X q $end
$upscope $end
$scope module dff_sum1 $end
$var wire 1 % clk $end
$var wire 1 Y d $end
$var wire 1 ' rst $end
$var reg 1 Z q $end
$upscope $end
$scope module dff_sum2 $end
$var wire 1 % clk $end
$var wire 1 [ d $end
$var wire 1 ' rst $end
$var reg 1 \ q $end
$upscope $end
$scope module dff_sum3 $end
$var wire 1 % clk $end
$var wire 1 ] d $end
$var wire 1 ' rst $end
$var reg 1 ^ q $end
$upscope $end
$scope module dff_sum4 $end
$var wire 1 % clk $end
$var wire 1 _ d $end
$var wire 1 ' rst $end
$var reg 1 ` q $end
$upscope $end
$scope module pg $end
$var wire 5 a a [4:0] $end
$var wire 5 b b [4:0] $end
$var wire 5 c g [4:0] $end
$var wire 5 d p [4:0] $end
$upscope $end
$upscope $end
$upscope $end
$enddefinitions $end
$comment Show the parameter values. $end
$dumpall
$end
#0
$dumpvars
bx d
bx c
bx b
bx a
x`
x_
x^
x]
x\
x[
xZ
xY
xX
xW
xV
0U
xT
0S
xR
0Q
xP
0O
xN
0M
xL
0K
xJ
0I
xH
0G
xF
0E
xD
0C
bx0 B
bx A
bxz @
bx ?
x>
x=
x<
x;
x:
x9
x8
x7
x6
x5
bx 4
bx 3
bx0 2
x1
bx 0
bx /
bx .
bx -
b0 ,
b0 +
bx *
bx )
b0 (
1'
bx &
0%
b0 $
b0 #
x"
bx !
$end
#5000
01
0[
0]
0_
0Y
1>
0W
1=
1<
1;
1:
19
18
17
16
15
b1111z @
b0 -
b0 2
b0 B
b0 /
b0 ?
b0 d
b0 0
b0 A
b0 c
0D
0F
0H
0J
b0 4
b0 a
0L
0N
0P
0R
0T
b0 3
b0 b
0V
0X
0Z
0\
0^
b0 !
b0 .
0`
0"
1%
#10000
0%
#15000
1%
#20000
0%
b0 *
b0 )
0'
#25000
1%
#30000
0%
#35000
1%
#40000
1M
0%
b1 $
b1 ,
b1 *
b0 &
#45000
1W
b1 -
b1 /
b1 ?
b1 d
b1 3
b1 b
1N
1%
#50000
0%
#55000
b1 !
b1 .
1X
1%
#60000
0M
1O
0%
b10 $
b10 ,
b10 *
b1 &
#65000
0W
1Y
b10 -
b10 /
b10 ?
b10 d
0N
b10 3
b10 b
1P
1%
#70000
0%
#75000
1Z
b10 !
b10 .
0X
1%
#80000
1M
0%
b11 $
b11 ,
b11 *
b10 &
#85000
1W
b11 -
b11 /
b11 ?
b11 d
b11 3
b11 b
1N
1%
#90000
0%
#95000
b11 !
b11 .
1X
1%
#100000
0M
0O
1Q
0%
b100 $
b100 ,
b100 *
b11 &
#105000
0W
0Y
1[
b100 -
b100 /
b100 ?
b100 d
0N
0P
b100 3
b100 b
1R
1%
#110000
0%
#115000
1\
0Z
b100 !
b100 .
0X
1%
#120000
1M
0%
b101 $
b101 ,
b101 *
b100 &
#125000
1W
b101 -
b101 /
b101 ?
b101 d
b101 3
b101 b
1N
1%
#130000
0%
#135000
b101 !
b101 .
1X
1%
#140000
0M
1O
0%
b110 $
b110 ,
b110 *
b101 &
#145000
0W
1Y
b110 -
b110 /
b110 ?
b110 d
0N
b110 3
b110 b
1P
1%
#150000
0%
#155000
1Z
b110 !
b110 .
0X
1%
#160000
1M
0%
b111 $
b111 ,
b111 *
b110 &
#165000
1W
b111 -
b111 /
b111 ?
b111 d
b111 3
b111 b
1N
1%
#170000
0%
#175000
b111 !
b111 .
1X
1%
#180000
0M
0O
0Q
1S
0%
b1000 $
b1000 ,
b1000 *
b111 &
#185000
0W
0Y
0[
1]
b1000 -
b1000 /
b1000 ?
b1000 d
0N
0P
0R
b1000 3
b1000 b
1T
1%
#190000
0%
#195000
1^
0\
0Z
b1000 !
b1000 .
0X
1%
#200000
1M
0%
b1001 $
b1001 ,
b1001 *
b1000 &
#205000
1W
b1001 -
b1001 /
b1001 ?
b1001 d
b1001 3
b1001 b
1N
1%
#210000
0%
#215000
b1001 !
b1001 .
1X
1%
#220000
0M
1O
0%
b1010 $
b1010 ,
b1010 *
b1001 &
#225000
0W
1Y
b1010 -
b1010 /
b1010 ?
b1010 d
0N
b1010 3
b1010 b
1P
1%
#230000
0%
#235000
1Z
b1010 !
b1010 .
0X
1%
#240000
1M
0%
b1011 $
b1011 ,
b1011 *
b1010 &
#245000
1W
b1011 -
b1011 /
b1011 ?
b1011 d
b1011 3
b1011 b
1N
1%
#250000
0%
#255000
b1011 !
b1011 .
1X
1%
#260000
0M
0O
1Q
0%
b1100 $
b1100 ,
b1100 *
b1011 &
#265000
0W
0Y
1[
b1100 -
b1100 /
b1100 ?
b1100 d
0N
0P
b1100 3
b1100 b
1R
1%
#270000
0%
#275000
1\
0Z
b1100 !
b1100 .
0X
1%
#280000
1M
0%
b1101 $
b1101 ,
b1101 *
b1100 &
#285000
1W
b1101 -
b1101 /
b1101 ?
b1101 d
b1101 3
b1101 b
1N
1%
#290000
0%
#295000
b1101 !
b1101 .
1X
1%
#300000
0M
1O
0%
b1110 $
b1110 ,
b1110 *
b1101 &
#305000
0W
1Y
b1110 -
b1110 /
b1110 ?
b1110 d
0N
b1110 3
b1110 b
1P
1%
#310000
0%
#315000
1Z
b1110 !
b1110 .
0X
1%
#320000
1M
0%
b1111 $
b1111 ,
b1111 *
b1110 &
#325000
1W
b1111 -
b1111 /
b1111 ?
b1111 d
b1111 3
b1111 b
1N
1%
#330000
0%
#335000
b1111 !
b1111 .
1X
1%
#340000
0M
0O
0Q
0S
1U
0%
b10000 $
b10000 ,
b10000 *
b1111 &
#345000
0W
0Y
0[
0]
1_
b10000 -
b10000 /
b10000 ?
b10000 d
0N
0P
0R
0T
b10000 3
b10000 b
1V
1%
#350000
0%
#355000
1`
0^
0\
0Z
b10000 !
b10000 .
0X
1%
#360000
1M
0%
b10001 $
b10001 ,
b10001 *
b10000 &
#365000
1W
b10001 -
b10001 /
b10001 ?
b10001 d
b10001 3
b10001 b
1N
1%
#370000
0%
#375000
b10001 !
b10001 .
1X
1%
#380000
0M
1O
0%
b10010 $
b10010 ,
b10010 *
b10001 &
#385000
0W
1Y
b10010 -
b10010 /
b10010 ?
b10010 d
0N
b10010 3
b10010 b
1P
1%
#390000
0%
#395000
1Z
b10010 !
b10010 .
0X
1%
#400000
1M
0%
b10011 $
b10011 ,
b10011 *
b10010 &
#405000
1W
b10011 -
b10011 /
b10011 ?
b10011 d
b10011 3
b10011 b
1N
1%
#410000
0%
#415000
b10011 !
b10011 .
1X
1%
#420000
0M
0O
1Q
0%
b10100 $
b10100 ,
b10100 *
b10011 &
#425000
0W
0Y
1[
b10100 -
b10100 /
b10100 ?
b10100 d
0N
0P
b10100 3
b10100 b
1R
1%
#430000
0%
#435000
1\
0Z
b10100 !
b10100 .
0X
1%
#440000
1M
0%
b10101 $
b10101 ,
b10101 *
b10100 &
#445000
1W
b10101 -
b10101 /
b10101 ?
b10101 d
b10101 3
b10101 b
1N
1%
#450000
0%
#455000
b10101 !
b10101 .
1X
1%
#460000
0M
1O
0%
b10110 $
b10110 ,
b10110 *
b10101 &
#465000
0W
1Y
b10110 -
b10110 /
b10110 ?
b10110 d
0N
b10110 3
b10110 b
1P
1%
#470000
0%
#475000
1Z
b10110 !
b10110 .
0X
1%
#480000
1M
0%
b10111 $
b10111 ,
b10111 *
b10110 &
#485000
1W
b10111 -
b10111 /
b10111 ?
b10111 d
b10111 3
b10111 b
1N
1%
#490000
0%
#495000
b10111 !
b10111 .
1X
1%
#500000
0M
0O
0Q
1S
0%
b11000 $
b11000 ,
b11000 *
b10111 &
#505000
0W
0Y
0[
1]
b11000 -
b11000 /
b11000 ?
b11000 d
0N
0P
0R
b11000 3
b11000 b
1T
1%
#510000
0%
#515000
1^
0\
0Z
b11000 !
b11000 .
0X
1%
#520000
1M
0%
b11001 $
b11001 ,
b11001 *
b11000 &
#525000
1W
b11001 -
b11001 /
b11001 ?
b11001 d
b11001 3
b11001 b
1N
1%
#530000
0%
#535000
b11001 !
b11001 .
1X
1%
#540000
0M
1O
0%
b11010 $
b11010 ,
b11010 *
b11001 &
#545000
0W
1Y
b11010 -
b11010 /
b11010 ?
b11010 d
0N
b11010 3
b11010 b
1P
1%
#550000
0%
#555000
1Z
b11010 !
b11010 .
0X
1%
#560000
1M
0%
b11011 $
b11011 ,
b11011 *
b11010 &
#565000
1W
b11011 -
b11011 /
b11011 ?
b11011 d
b11011 3
b11011 b
1N
1%
#570000
0%
#575000
b11011 !
b11011 .
1X
1%
#580000
0M
0O
1Q
0%
b11100 $
b11100 ,
b11100 *
b11011 &
#585000
0W
0Y
1[
b11100 -
b11100 /
b11100 ?
b11100 d
0N
0P
b11100 3
b11100 b
1R
1%
#590000
0%
#595000
1\
0Z
b11100 !
b11100 .
0X
1%
#600000
1M
0%
b11101 $
b11101 ,
b11101 *
b11100 &
#605000
1W
b11101 -
b11101 /
b11101 ?
b11101 d
b11101 3
b11101 b
1N
1%
#610000
0%
#615000
b11101 !
b11101 .
1X
1%
#620000
0M
1O
0%
b11110 $
b11110 ,
b11110 *
b11101 &
#625000
0W
1Y
b11110 -
b11110 /
b11110 ?
b11110 d
0N
b11110 3
b11110 b
1P
1%
#630000
0%
#635000
1Z
b11110 !
b11110 .
0X
1%
#640000
1M
0%
b11111 $
b11111 ,
b11111 *
b11110 &
#645000
1W
b11111 -
b11111 /
b11111 ?
b11111 d
b11111 3
b11111 b
1N
1%
#650000
0%
#655000
b11111 !
b11111 .
1X
1%
#660000
0M
0O
0Q
0S
0U
1C
0%
b0 $
b0 ,
b1 #
b1 +
b1 )
b0 *
b11111 &
#665000
0Y
0[
0]
0_
b1 -
b1 /
b1 ?
b1 d
b1 4
b1 a
1D
0N
0P
0R
0T
b0 3
b0 b
0V
1%
#670000
0%
#675000
0`
0^
0\
b1 !
b1 .
0Z
1%
#680000
1M
0%
b1 $
b1 ,
b1 *
b1 &
#685000
1Y
0W
b10 -
b10 2
b10 B
b0 /
b0 ?
b0 d
b1 0
b1 A
b1 c
b1 3
b1 b
1N
1%
#690000
0%
#695000
1Z
b10 !
b10 .
0X
1%
#700000
0M
1O
0%
b10 $
b10 ,
b10 *
b10 &
#705000
1W
1Y
b11 -
b0 2
b0 B
b11 /
b11 ?
b11 d
b0 0
b0 A
b0 c
0N
b10 3
b10 b
1P
1%
#710000
0%
#715000
b11 !
b11 .
1X
1%
#720000
1M
0%
b11 $
b11 ,
b11 *
b11 &
#725000
1[
0Y
0W
05
b100 -
b110 2
b110 B
b10 /
b10 ?
b10 d
b1 0
b1 A
b1 c
b11 3
b11 b
1N
1%
#730000
0%
#735000
1\
0Z
b100 !
b100 .
0X
1%
#740000
0M
0O
1Q
0%
b100 $
b100 ,
b100 *
b100 &
#745000
1W
0Y
1[
15
b101 -
b0 2
b0 B
b101 /
b101 ?
b101 d
b0 0
b0 A
b0 c
0N
0P
b100 3
b100 b
1R
1%
#750000
0%
#755000
b101 !
b101 .
1X
1%
#760000
1M
0%
b101 $
b101 ,
b101 *
b101 &
#765000
1Y
0W
b110 -
b10 2
b10 B
b100 /
b100 ?
b100 d
b1 0
b1 A
b1 c
b101 3
b101 b
1N
1%
#770000
0%
#775000
1Z
b110 !
b110 .
0X
1%
#780000
0M
1O
0%
b110 $
b110 ,
b110 *
b110 &
#785000
1W
1Y
b111 -
b0 2
b0 B
b111 /
b111 ?
b111 d
b0 0
b0 A
b0 c
0N
b110 3
b110 b
1P
1%
#790000
0%
#795000
b111 !
b111 .
1X
1%
#800000
1M
0%
b111 $
b111 ,
b111 *
b111 &
#805000
0[
1]
0Y
0W
07
05
b1000 -
b1110 2
b1110 B
b110 /
b110 ?
b110 d
b1 0
b1 A
b1 c
b111 3
b111 b
1N
1%
#810000
0%
#815000
1^
0\
0Z
b1000 !
b1000 .
0X
1%
#820000
0M
0O
0Q
1S
0%
b1000 $
b1000 ,
b1000 *
b1000 &
#825000
1W
0Y
0[
1]
17
15
b1001 -
b0 2
b0 B
b1001 /
b1001 ?
b1001 d
b0 0
b0 A
b0 c
0N
0P
0R
b1000 3
b1000 b
1T
1%
#830000
0%
#835000
b1001 !
b1001 .
1X
1%
#840000
1M
0%
b1001 $
b1001 ,
b1001 *
b1001 &
#845000
1Y
0W
b1010 -
b10 2
b10 B
b1000 /
b1000 ?
b1000 d
b1 0
b1 A
b1 c
b1001 3
b1001 b
1N
1%
#850000
0%
#855000
1Z
b1010 !
b1010 .
0X
1%
#860000
0M
1O
0%
b1010 $
b1010 ,
b1010 *
b1010 &
#865000
1W
1Y
b1011 -
b0 2
b0 B
b1011 /
b1011 ?
b1011 d
b0 0
b0 A
b0 c
0N
b1010 3
b1010 b
1P
1%
#870000
0%
#875000
b1011 !
b1011 .
1X
1%
#880000
1M
0%
b1011 $
b1011 ,
b1011 *
b1011 &
#885000
1[
0Y
0W
05
b1100 -
b110 2
b110 B
b1010 /
b1010 ?
b1010 d
b1 0
b1 A
b1 c
b1011 3
b1011 b
1N
1%
#890000
0%
#895000
1\
0Z
b1100 !
b1100 .
0X
1%
#900000
0M
0O
1Q
0%
b1100 $
b1100 ,
b1100 *
b1100 &
#905000
1W
0Y
1[
15
b1101 -
b0 2
b0 B
b1101 /
b1101 ?
b1101 d
b0 0
b0 A
b0 c
0N
0P
b1100 3
b1100 b
1R
1%
#910000
0%
#915000
b1101 !
b1101 .
1X
1%
#920000
1M
0%
b1101 $
b1101 ,
b1101 *
b1101 &
#925000
1Y
0W
b1110 -
b10 2
b10 B
b1100 /
b1100 ?
b1100 d
b1 0
b1 A
b1 c
b1101 3
b1101 b
1N
1%
#930000
0%
#935000
1Z
b1110 !
b1110 .
0X
1%
#940000
0M
1O
0%
b1110 $
b1110 ,
b1110 *
b1110 &
#945000
1W
1Y
b1111 -
b0 2
b0 B
b1111 /
b1111 ?
b1111 d
b0 0
b0 A
b0 c
0N
b1110 3
b1110 b
1P
1%
#950000
0%
#955000
b1111 !
b1111 .
1X
1%
#960000
1M
0%
b1111 $
b1111 ,
b1111 *
b1111 &
#965000
0[
0]
1_
0Y
0W
0:
07
05
b10000 -
b11110 2
b11110 B
b1110 /
b1110 ?
b1110 d
b1 0
b1 A
b1 c
b1111 3
b1111 b
1N
1%
#970000
0%
#975000
1`
0^
0\
0Z
b10000 !
b10000 .
0X
1%
#980000
0M
0O
0Q
0S
1U
0%
b10000 $
b10000 ,
b10000 *
b10000 &
#985000
1W
0Y
0[
0]
1_
1:
17
15
b10001 -
b0 2
b0 B
b10001 /
b10001 ?
b10001 d
b0 0
b0 A
b0 c
0N
0P
0R
0T
b10000 3
b10000 b
1V
1%
#990000
0%
#995000
b10001 !
b10001 .
1X
1%
#1000000
1M
0%
b10001 $
b10001 ,
b10001 *
b10001 &
#1005000
1Y
0W
b10010 -
b10 2
b10 B
b10000 /
b10000 ?
b10000 d
b1 0
b1 A
b1 c
b10001 3
b10001 b
1N
1%
#1010000
0%
#1015000
1Z
b10010 !
b10010 .
0X
1%
#1020000
0M
1O
0%
b10010 $
b10010 ,
b10010 *
b10010 &
#1025000
1W
1Y
b10011 -
b0 2
b0 B
b10011 /
b10011 ?
b10011 d
b0 0
b0 A
b0 c
0N
b10010 3
b10010 b
1P
1%
#1030000
0%
#1035000
b10011 !
b10011 .
1X
1%
#1040000
1M
0%
b10011 $
b10011 ,
b10011 *
b10011 &
#1045000
1[
0Y
0W
05
b10100 -
b110 2
b110 B
b10010 /
b10010 ?
b10010 d
b1 0
b1 A
b1 c
b10011 3
b10011 b
1N
1%
#1050000
0%
#1055000
1\
0Z
b10100 !
b10100 .
0X
1%
#1060000
0M
0O
1Q
0%
b10100 $
b10100 ,
b10100 *
b10100 &
#1065000
1W
0Y
1[
15
b10101 -
b0 2
b0 B
b10101 /
b10101 ?
b10101 d
b0 0
b0 A
b0 c
0N
0P
b10100 3
b10100 b
1R
1%
#1070000
0%
#1075000
b10101 !
b10101 .
1X
1%
#1080000
1M
0%
b10101 $
b10101 ,
b10101 *
b10101 &
#1085000
1Y
0W
b10110 -
b10 2
b10 B
b10100 /
b10100 ?
b10100 d
b1 0
b1 A
b1 c
b10101 3
b10101 b
1N
1%
#1090000
0%
#1095000
1Z
b10110 !
b10110 .
0X
1%
#1100000
0M
1O
0%
b10110 $
b10110 ,
b10110 *
b10110 &
#1105000
1W
1Y
b10111 -
b0 2
b0 B
b10111 /
b10111 ?
b10111 d
b0 0
b0 A
b0 c
0N
b10110 3
b10110 b
1P
1%
#1110000
0%
#1115000
b10111 !
b10111 .
1X
1%
#1120000
1M
0%
b10111 $
b10111 ,
b10111 *
b10111 &
#1125000
0[
1]
0Y
0W
07
05
b11000 -
b1110 2
b1110 B
b10110 /
b10110 ?
b10110 d
b1 0
b1 A
b1 c
b10111 3
b10111 b
1N
1%
#1130000
0%
#1135000
1^
0\
0Z
b11000 !
b11000 .
0X
1%
#1140000
0M
0O
0Q
1S
0%
b11000 $
b11000 ,
b11000 *
b11000 &
#1145000
1W
0Y
0[
1]
17
15
b11001 -
b0 2
b0 B
b11001 /
b11001 ?
b11001 d
b0 0
b0 A
b0 c
0N
0P
0R
b11000 3
b11000 b
1T
1%
#1150000
0%
#1155000
b11001 !
b11001 .
1X
1%
#1160000
1M
0%
b11001 $
b11001 ,
b11001 *
b11001 &
#1165000
1Y
0W
b11010 -
b10 2
b10 B
b11000 /
b11000 ?
b11000 d
b1 0
b1 A
b1 c
b11001 3
b11001 b
1N
1%
#1170000
0%
#1175000
1Z
b11010 !
b11010 .
0X
1%
#1180000
0M
1O
0%
b11010 $
b11010 ,
b11010 *
b11010 &
#1185000
1W
1Y
b11011 -
b0 2
b0 B
b11011 /
b11011 ?
b11011 d
b0 0
b0 A
b0 c
0N
b11010 3
b11010 b
1P
1%
#1190000
0%
#1195000
b11011 !
b11011 .
1X
1%
#1200000
1M
0%
b11011 $
b11011 ,
b11011 *
b11011 &
#1205000
1[
0Y
0W
05
b11100 -
b110 2
b110 B
b11010 /
b11010 ?
b11010 d
b1 0
b1 A
b1 c
b11011 3
b11011 b
1N
1%
#1210000
0%
#1215000
1\
0Z
b11100 !
b11100 .
0X
1%
#1220000
0M
0O
1Q
0%
b11100 $
b11100 ,
b11100 *
b11100 &
#1225000
1W
0Y
1[
15
b11101 -
b0 2
b0 B
b11101 /
b11101 ?
b11101 d
b0 0
b0 A
b0 c
0N
0P
b11100 3
b11100 b
1R
1%
#1230000
0%
#1235000
b11101 !
b11101 .
1X
1%
#1240000
1M
0%
b11101 $
b11101 ,
b11101 *
b11101 &
#1245000
1Y
0W
b11110 -
b10 2
b10 B
b11100 /
b11100 ?
b11100 d
b1 0
b1 A
b1 c
b11101 3
b11101 b
1N
1%
#1250000
0%
#1255000
1Z
b11110 !
b11110 .
0X
1%
#1260000
0M
1O
0%
b11110 $
b11110 ,
b11110 *
b11110 &
#1265000
1W
1Y
b11111 -
b0 2
b0 B
b11111 /
b11111 ?
b11111 d
b0 0
b0 A
b0 c
0N
b11110 3
b11110 b
1P
1%
#1270000
0%
#1275000
b11111 !
b11111 .
1X
1%
#1280000
1M
0%
b11111 $
b11111 ,
b11111 *
b11111 &
#1285000
11
0[
0]
0_
0Y
0>
0W
0:
07
05
b0 -
b111110 2
b111110 B
b11110 /
b11110 ?
b11110 d
b1 0
b1 A
b1 c
b11111 3
b11111 b
1N
1%
#1290000
0%
#1295000
1"
0`
0^
0\
0Z
b0 !
b0 .
0X
1%
#1300000
0M
0O
0Q
0S
0U
0C
1E
0%
b0 $
b0 ,
b10 #
b10 +
b10 )
b0 *
b100000 &
#1305000
01
1Y
1>
0[
0]
0_
1:
17
15
b10 -
b0 2
b0 B
b10 /
b10 ?
b10 d
b0 0
b0 A
b0 c
0D
b10 4
b10 a
1F
0N
0P
0R
0T
b0 3
b0 b
0V
1%
#1310000
0%
#1315000
0"
b10 !
b10 .
1Z
1%
#1320000
1M
0%
b1 $
b1 ,
b1 *
b10 &
#1325000
1W
b11 -
b11 /
b11 ?
b11 d
b1 3
b1 b
1N
1%
#1330000
0%
#1335000
b11 !
b11 .
1X
1%
#1340000
0M
1O
0%
b10 $
b10 ,
b10 *
b11 &
#1345000
1[
b100 2
b100 B
0W
0Y
b1110z @
b100 -
b0 /
b0 ?
b0 d
b10 0
b10 A
b10 c
0N
b10 3
b10 b
1P
1%
#1350000
0%
#1355000
1\
0Z
b100 !
b100 .
0X
1%
#1360000
1M
0%
b11 $
b11 ,
b11 *
b100 &
#1365000
1W
b101 -
b1 /
b1 ?
b1 d
b11 3
b11 b
1N
1%
#1370000
0%
#1375000
b101 !
b101 .
1X
1%
#1380000
0M
0O
1Q
0%
b100 $
b100 ,
b100 *
b101 &
#1385000
b0 2
b0 B
0W
1Y
1[
b1111z @
b110 -
b110 /
b110 ?
b110 d
b0 0
b0 A
b0 c
0N
0P
b100 3
b100 b
1R
1%
#1390000
0%
#1395000
1Z
b110 !
b110 .
0X
1%
