Verilog/main.v
module dff(
    input wire clk,
    input wire rst,
    input wire d,
    output reg q
);
always @(posedge clk) begin
    if (rst)
        q <= 0;
    else
        q <= d;
end
endmodule

module pg_logic (
    input wire [4:0] a,
    input wire [4:0] b,
    output wire [4:0] p,    
    output wire [4:0] g        
);
    assign p   = a ^ b;   
    assign g   = a & b; 
endmodule


module cla_carry (
    input wire [4:0] p,
    input wire [4:0] g,
    output wire [5:0] c
);
    wire [4:0] g_bar;
    wire t2_1, t3_1, t3_2, t4_1, t4_2, t4_3, t5_1, t5_2, t5_3, t5_4;
    
    assign c[0] = 1'b0;
    assign c[1] = g[0];
    
    // Invert g signals
    not(g_bar[1], g[1]);
    not(g_bar[2], g[2]);
    not(g_bar[3], g[3]);
    not(g_bar[4], g[4]);
    
    // c[2] = g[1] | (p[1] & g[0])
    nand(t2_1, p[1], g[0]);
    nand(c[2], g_bar[1], t2_1);

    // c[3] = g[2] | (p[2] & g[1]) | (p[2] & p[1] & g[0])
    nand(t3_1, p[2], g[1]);
    nand(t3_2, p[2], p[1], g[0]);
    nand(c[3], g_bar[2], t3_1, t3_2);

    // c[4] = g[3] | (p[3] & g[2]) | (p[3] & p[2] & g[1]) | (p[3] & p[2] & p[1] & g[0])
    nand(t4_1, p[3], g[2]);
    nand(t4_2, p[3], p[2], g[1]);
    nand(t4_3, p[3], p[2], p[1], g[0]);
    nand(c[4], g_bar[3], t4_1, t4_2, t4_3);
    
    // c[5] = g[4] | (p[4] & g[3]) | (p[4] & p[3] & g[2]) | (p[4] & p[3] & p[2] & g[1]) | (p[4] & p[3] & p[2] & p[1] & g[0])
    nand(t5_1, p[4], g[3]);
    nand(t5_2, p[4], p[3], g[2]);
    nand(t5_3, p[4], p[3], p[2], g[1]);
    nand(t5_4, p[4], p[3], p[2], p[1], g[0]);
    nand(c[5], g_bar[4], t5_1, t5_2, t5_3, t5_4);
endmodule


module cla_adder_5bit (
    input wire clk,
    input wire rst,
    input wire [4:0] a,
    input wire [4:0] b,
    output wire [4:0] sum,
    output wire cout
);

    wire [4:0] a_reg, b_reg;
    wire [4:0] p, g;
    wire [5:0] c;
    wire [4:0] sum_int;
    wire cout_int;
    
    dff dff_a0 (.clk(clk), .rst(rst), .d(a[0]), .q(a_reg[0]));
    dff dff_a1 (.clk(clk), .rst(rst), .d(a[1]), .q(a_reg[1]));
    dff dff_a2 (.clk(clk), .rst(rst), .d(a[2]), .q(a_reg[2]));
    dff dff_a3 (.clk(clk), .rst(rst), .d(a[3]), .q(a_reg[3]));
    dff dff_a4 (.clk(clk), .rst(rst), .d(a[4]), .q(a_reg[4]));
    
    dff dff_b0 (.clk(clk), .rst(rst), .d(b[0]), .q(b_reg[0]));
    dff dff_b1 (.clk(clk), .rst(rst), .d(b[1]), .q(b_reg[1]));
    dff dff_b2 (.clk(clk), .rst(rst), .d(b[2]), .q(b_reg[2]));
    dff dff_b3 (.clk(clk), .rst(rst), .d(b[3]), .q(b_reg[3]));
    dff dff_b4 (.clk(clk), .rst(rst), .d(b[4]), .q(b_reg[4]));
    
    pg_logic pg (
        .a(a_reg),
        .b(b_reg),
        .p(p),
        .g(g)
    );
    
    cla_carry cla (
        .p(p),
        .g(g),
        .c(c)
    );
    assign sum_int = p ^ c[4:0];
    assign cout_int = c[5];
    
    dff dff_sum0 (.clk(clk), .rst(rst), .d(sum_int[0]), .q(sum[0]));
    dff dff_sum1 (.clk(clk), .rst(rst), .d(sum_int[1]), .q(sum[1]));
    dff dff_sum2 (.clk(clk), .rst(rst), .d(sum_int[2]), .q(sum[2]));
    dff dff_sum3 (.clk(clk), .rst(rst), .d(sum_int[3]), .q(sum[3]));
    dff dff_sum4 (.clk(clk), .rst(rst), .d(sum_int[4]), .q(sum[4]));
    dff dff_cout (.clk(clk), .rst(rst), .d(cout_int), .q(cout));
    
endmodule

Verilog/tb.v
`timescale 1ns/1ps

module tb_cla_adder_5bit;

    // DUT inputs
    reg clk;
    reg rst;
    reg [4:0] a;
    reg [4:0] b;

    // DUT outputs
    wire [4:0] sum;
    wire cout;

    // Instantiate DUT
    cla_adder_5bit uut (
        .clk(clk),
        .rst(rst),
        .a(a),
        .b(b),
        .sum(sum),
        .cout(cout)
    );

    // Clock generation: 10 ns period (100 MHz)
    always #5 clk = ~clk;

    // Dump waveforms for GTKWave
    initial begin
        $dumpfile("cla_adder_5bit.vcd");
        $dumpvars(0, tb_cla_adder_5bit);
    end

    // Test procedure
    initial begin
        // Initialize
        clk = 0;
        rst = 1;
        a = 0;
        b = 0;
        
        // Apply reset for 2 clock cycles
        #20;
        rst = 0;
        
        // Test case 1: Simple add
        a = 5'b00011;   // 3
        b = 5'b00101;   // 5
        #20;
        
        // Test case 2: Larger numbers
        a = 5'b01111;   // 15
        b = 5'b00001;   // 1
        #20;

        // Test case 3: More larger numbers
        a = 5'b10101;   // 21
        b = 5'b01011;   // 11
        #20;

        // Test case 4: All ones (carry overflow check)
        a = 5'b11111;   // 31
        b = 5'b11111;   // 31
        #20;

        // Test case 5: Random pattern
        a = 5'b10010;
        b = 5'b01101;
        #20;

        // End simulation
        #20;
        $finish;
    end

    // Monitor results
    initial begin
        $display("Time\tclk\trst\ta\tb\t|\tsum\tcout");
        $monitor("%0t\t%b\t%b\t%05b\t%05b\t|\t%05b\t%b", 
                 $time, clk, rst, a, b, sum, cout);
    end
endmodule

Verilog/cla_adder_5bit.vcd
$date
	Wed Dec 03 20:20:04 2025
$end
$version
	Icarus Verilog
$end
$timescale
	1ps
$end
$scope module tb_cla_adder_5bit $end
$var wire 5 ! sum [4:0] $end
$var wire 1 " cout $end
$var reg 5 # a [4:0] $end
$var reg 5 $ b [4:0] $end
$var reg 1 % clk $end
$var reg 1 & rst $end
$scope module uut $end
$var wire 5 ' a [4:0] $end
$var wire 5 ( b [4:0] $end
$var wire 1 % clk $end
$var wire 1 & rst $end
$var wire 5 ) sum_int [4:0] $end
$var wire 5 * sum [4:0] $end
$var wire 5 + p [4:0] $end
$var wire 5 , g [4:0] $end
$var wire 1 - cout_int $end
$var wire 1 " cout $end
$var wire 6 . c [5:0] $end
$var wire 5 / b_reg [4:0] $end
$var wire 5 0 a_reg [4:0] $end
$scope module cla $end
$var wire 1 1 t2_1 $end
$var wire 1 2 t3_1 $end
$var wire 1 3 t3_2 $end
$var wire 1 4 t4_1 $end
$var wire 1 5 t4_2 $end
$var wire 1 6 t4_3 $end
$var wire 1 7 t5_1 $end
$var wire 1 8 t5_2 $end
$var wire 1 9 t5_3 $end
$var wire 1 : t5_4 $end
$var wire 5 ; p [4:0] $end
$var wire 5 < g_bar [4:0] $end
$var wire 5 = g [4:0] $end
$var wire 6 > c [5:0] $end
$upscope $end
$scope module dff_a0 $end
$var wire 1 % clk $end
$var wire 1 ? d $end
$var wire 1 & rst $end
$var reg 1 @ q $end
$upscope $end
$scope module dff_a1 $end
$var wire 1 % clk $end
$var wire 1 A d $end
$var wire 1 & rst $end
$var reg 1 B q $end
$upscope $end
$scope module dff_a2 $end
$var wire 1 % clk $end
$var wire 1 C d $end
$var wire 1 & rst $end
$var reg 1 D q $end
$upscope $end
$scope module dff_a3 $end
$var wire 1 % clk $end
$var wire 1 E d $end
$var wire 1 & rst $end
$var reg 1 F q $end
$upscope $end
$scope module dff_a4 $end
$var wire 1 % clk $end
$var wire 1 G d $end
$var wire 1 & rst $end
$var reg 1 H q $end
$upscope $end
$scope module dff_b0 $end
$var wire 1 % clk $end
$var wire 1 I d $end
$var wire 1 & rst $end
$var reg 1 J q $end
$upscope $end
$scope module dff_b1 $end
$var wire 1 % clk $end
$var wire 1 K d $end
$var wire 1 & rst $end
$var reg 1 L q $end
$upscope $end
$scope module dff_b2 $end
$var wire 1 % clk $end
$var wire 1 M d $end
$var wire 1 & rst $end
$var reg 1 N q $end
$upscope $end
$scope module dff_b3 $end
$var wire 1 % clk $end
$var wire 1 O d $end
$var wire 1 & rst $end
$var reg 1 P q $end
$upscope $end
$scope module dff_b4 $end
$var wire 1 % clk $end
$var wire 1 Q d $end
$var wire 1 & rst $end
$var reg 1 R q $end
$upscope $end
$scope module dff_cout $end
$var wire 1 % clk $end
$var wire 1 - d $end
$var wire 1 & rst $end
$var reg 1 " q $end
$upscope $end
$scope module dff_sum0 $end
$var wire 1 % clk $end
$var wire 1 S d $end
$var wire 1 & rst $end
$var reg 1 T q $end
$upscope $end
$scope module dff_sum1 $end
$var wire 1 % clk $end
$var wire 1 U d $end
$var wire 1 & rst $end
$var reg 1 V q $end
$upscope $end
$scope module dff_sum2 $end
$var wire 1 % clk $end
$var wire 1 W d $end
$var wire 1 & rst $end
$var reg 1 X q $end
$upscope $end
$scope module dff_sum3 $end
$var wire 1 % clk $end
$var wire 1 Y d $end
$var wire 1 & rst $end
$var reg 1 Z q $end
$upscope $end
$scope module dff_sum4 $end
$var wire 1 % clk $end
$var wire 1 [ d $end
$var wire 1 & rst $end
$var reg 1 \ q $end
$upscope $end
$scope module pg $end
$var wire 5 ] a [4:0] $end
$var wire 5 ^ b [4:0] $end
$var wire 5 _ g [4:0] $end
$var wire 5 ` p [4:0] $end
$upscope $end
$upscope $end
$upscope $end
$enddefinitions $end
$comment Show the parameter values. $end
$dumpall
$end
#0
$dumpvars
bx `
bx _
bx ^
bx ]
x\
x[
xZ
xY
xX
xW
xV
xU
xT
xS
xR
0Q
xP
0O
xN
0M
xL
0K
xJ
0I
xH
0G
xF
0E
xD
0C
xB
0A
x@
0?
bx0 >
bx =
bxz <
bx ;
x:
x9
x8
x7
x6
x5
x4
x3
x2
x1
bx 0
bx /
bx0 .
x-
bx ,
bx +
bx *
bx )
b0 (
b0 '
1&
0%
b0 $
b0 #
x"
bx !
$end
#5000
0-
0W
0Y
0[
0U
1:
0S
19
18
17
16
15
14
13
12
11
b1111z <
b0 )
b0 .
b0 >
b0 +
b0 ;
b0 `
b0 ,
b0 =
b0 _
0@
0B
0D
0F
b0 0
b0 ]
0H
0J
0L
0N
0P
b0 /
b0 ^
0R
0T
0V
0X
0Z
b0 !
b0 *
0\
0"
1%
#10000
0%
#15000
1%
#20000
1I
1M
1?
1A
0%
b101 $
b101 (
b11 #
b11 '
0&
#25000
1Y
0U
0W
03
01
b1000 )
b1110 .
b1110 >
b110 +
b110 ;
b110 `
b1 ,
b1 =
b1 _
1@
b11 0
b11 ]
1B
1J
b101 /
b101 ^
1N
1%
#30000
0%
#35000
b1000 !
b1000 *
1Z
1%
#40000
0M
1C
1E
0%
b1 $
b1 (
b1111 #
b1111 '
#45000
1[
b11110 .
b11110 >
06
0Y
b10000 )
b1110 +
b1110 ;
b1110 `
1D
b1111 0
b1111 ]
1F
b1 /
b1 ^
0N
1%
#50000
0%
#55000
1\
b10000 !
b10000 *
0Z
1%
#60000
1K
1O
0A
0E
1G
0%
b1011 $
b1011 (
b10101 #
b10101 '
#65000
1-
b111110 .
b111110 >
0:
0[
b0 )
b11110 +
b11110 ;
b11110 `
0B
0F
b10101 0
b10101 ]
1H
1L
b1011 /
b1011 ^
1P
1%
#70000
0%
#75000
1"
b0 !
b0 *
0\
1%
#80000
1M
1Q
1A
1E
0%
b11111 $
b11111 (
b11111 #
b11111 '
#85000
1:
16
13
11
1U
1W
1Y
1[
b0z <
b11110 )
b0 +
b0 ;
b0 `
b11111 ,
b11111 =
b11111 _
1B
b11111 0
b11111 ]
1F
1N
b11111 /
b11111 ^
1R
1%
#90000
0%
#95000
1\
1Z
1X
b11110 !
b11110 *
1V
1%
#100000
0K
0Q
0?
0C
0E
0%
b1101 $
b1101 (
b10010 #
b10010 '
#105000
0-
1S
1U
1W
1Y
1[
b1111z <
b11111 )
b0 .
b0 >
b11111 +
b11111 ;
b11111 `
b0 ,
b0 =
b0 _
0@
0D
b10010 0
b10010 ]
0F
0L
b1101 /
b1101 ^
0R
1%
#110000
0%
#115000
0"
b11111 !
b11111 *
1T
1%
